{"sections":{"main-page":{"type":"main-page","settings":{"heading_size":"title-lg tracking-heading","heading_tag":"h1","text_size":"text-base","padding_top":72,"padding_bottom":120,"divider":false,"narrow":true,"rounded":false}},"17157682575ad8f603":{"type":"apps","blocks":{"forms_inline_QznU9a":{"type":"shopify:\/\/apps\/forms\/blocks\/inline\/8744a304-fcb1-4347-b211-bb6b4759a76a","settings":{"form_id":"100787","text_color":"#202020","button_background_color":"#202020","button_label_color":"#ffffff","links_color":"#1878b9","errors_color":"#e02229","text_alignment":"center","form_alignment":"center","padding_top":0,"padding_bottom":0,"padding_right":0,"padding_left":0}}},"block_order":["forms_inline_QznU9a"],"disabled":true,"settings":{"color_text":"","color_background":"","gradient_background":"","color_highlight":"","gradient_highlight":"","color_button_text":"","color_button_background":"","color_button_gradient":"","padding_top":72,"padding_bottom":72,"divider":false,"full_width":false,"rounded":false}},"collection_list_kg7KnE":{"type":"collection-list","blocks":{"collection_ibDQUq":{"type":"collection","settings":{"collection":"multipanel-tile-range","title":"The Tile Range","description":"","overlay_content":false,"color_text":"#ffffff","color_overlay":"#000000","overlay_opacity":30}},"collection_UpTM7a":{"type":"collection","settings":{"collection":"multipanel-classic","title":"The Classic Range","description":"","overlay_content":false,"color_text":"#ffffff","color_overlay":"#000000","overlay_opacity":30}},"collection_JTqVjX":{"type":"collection","settings":{"collection":"multipanel-contemporary","title":"The Contemporary Collection","description":"","overlay_content":false,"color_text":"#ffffff","color_overlay":"#000000","overlay_opacity":30}},"collection_JtXJxa":{"type":"collection","settings":{"collection":"multipanel-pure","title":"The Pure Collection","description":"","overlay_content":false,"color_text":"#ffffff","color_overlay":"#000000","overlay_opacity":30}},"collection_URAcUM":{"type":"collection","settings":{"collection":"linda-barker","title":"The Linda Barker Collection","description":"","overlay_content":false,"color_text":"#ffffff","color_overlay":"#000000","overlay_opacity":30}},"collection_ATd6TE":{"type":"collection","settings":{"collection":"multipanel-trims-consumables","title":"Trims & Consumables","description":"","overlay_content":false,"color_text":"#ffffff","color_overlay":"#000000","overlay_opacity":30}}},"block_order":["collection_ibDQUq","collection_UpTM7a","collection_JTqVjX","collection_JtXJxa","collection_URAcUM","collection_ATd6TE"],"disabled":true,"settings":{"columns":5,"carousel_on_desktop":true,"image_type":"collection","image_ratio":"square","show_products_count":true,"show_view_all":false,"columns_mobile":"1","swipe_on_mobile":true,"heading":"","heading_size":"title-md","heading_alignment":"text-left md:items-end md:flex-row","heading_tag":"h2","subheading":"","description":"","highlighted_text":"none","highlighted_scribble":"circle","color_text":"","color_background":"","gradient_background":"","color_highlight":"","gradient_highlight":"","color_button_text":"","color_button_background":"","color_button_gradient":"","padding_top":72,"padding_bottom":72,"divider":false,"full_width":false,"rounded":false}},"collection_list_GW8TJw":{"type":"collection-list","blocks":{"collection_jkLJCp":{"type":"collection","settings":{"collection":"kudos-shower-trays","image":"shopify:\/\/shop_images\/Screenshot_2024-10-24_at_11.05.33.jpg","title":"Kstone","description":"","overlay_content":true,"color_text":"#ffffff","color_overlay":"#000000","overlay_opacity":30}},"collection_Tqt6V7":{"type":"collection","settings":{"collection":"shire-shower-trays","image":"shopify:\/\/shop_images\/Screenshot_2024-10-24_at_11.06.56.jpg","title":"Shire","description":"","overlay_content":true,"color_text":"#ffffff","color_overlay":"#000000","overlay_opacity":30}},"collection_wKtnkq":{"type":"collection","settings":{"collection":"roca-shower-tray","image":"shopify:\/\/shop_images\/Screenshot_2024-10-24_at_11.08.05.jpg","title":"Roca","description":"","overlay_content":true,"color_text":"#ffffff","color_overlay":"#000000","overlay_opacity":30}}},"block_order":["collection_jkLJCp","collection_Tqt6V7","collection_wKtnkq"],"settings":{"columns":3,"carousel_on_desktop":false,"image_type":"collection","image_ratio":"square","show_products_count":true,"show_view_all":false,"columns_mobile":"1","swipe_on_mobile":true,"heading":"Popular Ranges","heading_size":"title-md","heading_alignment":"text-center md:items-center","heading_tag":"h2","subheading":"","description":"","highlighted_text":"none","highlighted_scribble":"circle","color_text":"","color_background":"","gradient_background":"","color_highlight":"","gradient_highlight":"","color_button_text":"","color_button_background":"","color_button_gradient":"","padding_top":72,"padding_bottom":72,"divider":false,"full_width":false,"rounded":true}},"multicolumn_tzqQik":{"type":"multicolumn","blocks":{"column_CYr8da":{"type":"column","settings":{"show_border":false,"text_alignment":"left","text_alignment_mobile":"left","image":"shopify:\/\/shop_images\/Screenshot_2024-10-24_at_11.22.50.jpg","image_ratio":"square","heading":"Square Trays","heading_size":"text-lg-2xl","text":"","button_label":"","button_link":"shopify:\/\/collections\/square-shower-tray","highlighted_text":"none","highlighted_scribble":"circle"}},"column_UrYThJ":{"type":"column","settings":{"show_border":false,"text_alignment":"left","text_alignment_mobile":"left","image":"shopify:\/\/shop_images\/Screenshot_2024-10-24_at_11.26.36.jpg","image_ratio":"square","heading":"Quadrant Trays","heading_size":"text-lg-2xl","text":"","button_label":"","button_link":"shopify:\/\/collections\/quadrant-trays","highlighted_text":"none","highlighted_scribble":"circle"}},"column_KWmVEQ":{"type":"column","settings":{"show_border":false,"text_alignment":"left","text_alignment_mobile":"left","image":"shopify:\/\/shop_images\/Screenshot_2024-10-24_at_11.28.56.jpg","image_ratio":"square","heading":"Off-Set Quadrant Trays","heading_size":"text-lg-2xl","text":"","button_label":"","button_link":"shopify:\/\/collections\/off-set-quadrant","highlighted_text":"none","highlighted_scribble":"circle"}}},"block_order":["column_CYr8da","column_UrYThJ","column_KWmVEQ"],"settings":{"columns":4,"columns_mobile":"1","swipe_on_mobile":true,"heading":"Shop By Tray Type","heading_size":"title-md","heading_alignment":"text-center md:items-center","heading_tag":"h2","subheading":"","description":"","button_label":"","button_link":"","highlighted_text":"none","highlighted_scribble":"circle","color_text":"","color_background":"","gradient_background":"","color_highlight":"","gradient_highlight":"","color_button_text":"","color_button_background":"","color_button_gradient":"","padding_top":72,"padding_bottom":72,"divider":false,"full_width":false,"rounded":false}},"multicolumn_REJ4jg":{"type":"multicolumn","blocks":{"column_GcdKfD":{"type":"column","settings":{"show_border":false,"text_alignment":"left","text_alignment_mobile":"left","image":"shopify:\/\/shop_images\/Screenshot_2024-10-24_at_11.24.11.jpg","image_ratio":"adapt","heading":"Rectangular Trays","heading_size":"text-lg-2xl","text":"","button_label":"","button_link":"shopify:\/\/collections\/rectangular-shower-tray","highlighted_text":"none","highlighted_scribble":"circle"}},"column_6zcUK9":{"type":"column","settings":{"show_border":false,"text_alignment":"left","text_alignment_mobile":"left","image":"shopify:\/\/shop_images\/Screenshot_2024-10-24_at_11.31.51.jpg","image_ratio":"square","heading":"Walk-In Trays","heading_size":"text-lg-2xl","text":"","button_label":"","button_link":"shopify:\/\/collections\/walk-in-trays","highlighted_text":"none","highlighted_scribble":"circle"}},"column_mbwRUH":{"type":"column","settings":{"show_border":false,"text_alignment":"left","text_alignment_mobile":"left","image":"shopify:\/\/shop_images\/Screenshot_2024-10-24_at_11.33.03.jpg","image_ratio":"square","heading":"Black Trays","heading_size":"text-lg-2xl","text":"","button_label":"","button_link":"shopify:\/\/collections\/black-shower-trays","highlighted_text":"none","highlighted_scribble":"circle"}}},"block_order":["column_GcdKfD","column_6zcUK9","column_mbwRUH"],"settings":{"columns":4,"columns_mobile":"1","swipe_on_mobile":true,"heading":"","heading_size":"title-md","heading_alignment":"text-center md:items-center","heading_tag":"h2","subheading":"","description":"","button_label":"","button_link":"","highlighted_text":"none","highlighted_scribble":"circle","color_text":"","color_background":"","gradient_background":"","color_highlight":"","gradient_highlight":"","color_button_text":"","color_button_background":"","color_button_gradient":"","padding_top":72,"padding_bottom":72,"divider":false,"full_width":false,"rounded":false}}},"order":["main-page","17157682575ad8f603","collection_list_kg7KnE","collection_list_GW8TJw","multicolumn_tzqQik","multicolumn_REJ4jg"]}